artd_channels/__init__.py
artd_channels/admin.py
artd_channels/apps.py
artd_channels/models.py
artd_channels/signals.py
artd_channels/management/__init__.py
artd_channels/management/commands/__init__.py
artd_channels/management/commands/populate_channels.py
artd_channels/management/commands/populate_providers.py
artd_channels/migrations/0001_initial.py
artd_channels/migrations/0002_credentials.py
artd_channels/migrations/0003_messagges.py
artd_channels/migrations/0004_provider_rename_messagges_messagge_credential_and_more.py
artd_channels/migrations/0005_customerchannel.py
artd_channels/migrations/0006_customerchannel_order.py
artd_channels/migrations/0007_alter_customerchannel_unique_together.py
artd_channels/migrations/0008_alter_customerchannel_unique_together.py
artd_channels/migrations/0009_messagge_provider.py
artd_channels/migrations/0010_alter_messagge_messages.py
artd_channels/migrations/0011_alter_messagge_messages.py
artd_channels/migrations/__init__.py
artd_channels/utils/__init__.py
artd_channels/utils/email/__init__.py
artd_channels/utils/email/aws_email_util.py
artd_channels/utils/sms/__init__.py
artd_channels/utils/sms/aws_sms_util.py
artd_channels/utils/sms/labs_sms_util.py
artd_channels/utils/sms/data/__init__.py
artd_channels/utils/sms/data/labs_response.py
artd_channels/utils/whatsapp/__init__.py
artd_channels/utils/whatsapp/mb_send_wha.py
artd_channels/utils/whatsapp/messagebird_util.py
channel/__init__.py
channel/asgi.py
channel/settings.py
channel/urls.py
channel/wsgi.py
artd_channels-1.0.14.dist-info/LICENSE
artd_channels-1.0.14.dist-info/METADATA
artd_channels-1.0.14.dist-info/WHEEL
artd_channels-1.0.14.dist-info/top_level.txt
artd_channels-1.0.14.dist-info/RECORD
